databroker_pack/__init__.py
databroker_pack/_pack.py
databroker_pack/_unpack.py
databroker_pack/_utils.py
databroker_pack/_version.py
databroker_pack/commandline/__init__.py
databroker_pack/commandline/_utils.py
databroker_pack/commandline/pack.py
databroker_pack/commandline/unpack.py
databroker_pack/tests/__init__.py
databroker_pack/tests/conftest.py
databroker_pack/tests/test_cli.py
databroker_pack/tests/test_strict.py
databroker_pack-0.3.0.dist-info/AUTHORS.rst
databroker_pack-0.3.0.dist-info/LICENSE
databroker_pack-0.3.0.dist-info/METADATA
databroker_pack-0.3.0.dist-info/WHEEL
databroker_pack-0.3.0.dist-info/entry_points.txt
databroker_pack-0.3.0.dist-info/top_level.txt
databroker_pack-0.3.0.dist-info/RECORD
