Metadata-Version: 2.1
Name: databroker-pack
Version: 0.3.0
Summary: Tools for a portable databroker
Home-page: https://github.com/bluesky/databroker-pack
Author: Bluesky Collaboration
Author-email: dama@bnl.gov
License: BSD (3-clause)
Platform: UNKNOWN
Classifier: Development Status :: 2 - Pre-Alpha
Classifier: Natural Language :: English
Classifier: Programming Language :: Python :: 3
Requires-Python: >=3.6
Requires-Dist: databroker (>=1.0.5)
Requires-Dist: event-model
Requires-Dist: intake (>=0.5.5)
Requires-Dist: suitcase-jsonl
Requires-Dist: suitcase-msgpack
Requires-Dist: suitcase-utils
Requires-Dist: tqdm
